<?xml version = '1.0' encoding = 'UTF-8'?>
<Relation class="oracle.dbtools.crest.model.design.logical.Relation" name="Serv2" directorySegmentName="seg_0" id="D4115B66-6976-C829-35A4-4C124DEB5D32">
<createdBy>Usuario</createdBy>
<createdTime>2022-03-13 19:00:27 UTC</createdTime>
<ownerDesignName>ModelagemJK</ownerDesignName>
<engineerTo>
<item key="B7B5A3F6-07F9-4E22-08B4-E8C990FA94AC" value="true"/>
</engineerTo>
<sourcePk>4B087B87-AAB3-EFA1-294B-CF9485CEF1F4</sourcePk>
<identifying>false</identifying>
<optionalSource>true</optionalSource>
<optionalTarget>true</optionalTarget>
<sourceCardinality>1</sourceCardinality>
<sourceEntity>CB055FE8-B15F-F861-4DDB-B95CE598C0EE</sourceEntity>
<targetCardinalityString>*</targetCardinalityString>
<targetEntity>63F4EA7F-BB3D-3E48-F58A-AECA7A70526E</targetEntity>
<transferable>true</transferable>
<deleteRule>NO ACTION</deleteRule>
</Relation>
